idu/__init__.py
idu/__main__.py
idu-0.4.0.dist-info/METADATA
idu-0.4.0.dist-info/WHEEL
idu-0.4.0.dist-info/entry_points.txt
idu-0.4.0.dist-info/top_level.txt
idu-0.4.0.dist-info/RECORD
