Metadata-Version: 2.1
Name: idu
Version: 0.4.0
Summary: interactive disk usage analyser
Home-page: https://github.com/jftsang/idu
Author: J. M. F. Tsang
Author-email: j.m.f.tsang@cantab.net
License: MIT License
Platform: UNKNOWN
